{
  "status": "success",
  "data": {
    "resultType": "matrix",
    "result": [
      {
        "metric": {},
        "values": [
          [
            1499976630.781,
            "0"
          ],
          [
            1499976930.781,
            "0"
          ],
          [
            1499977230.781,
            "0"
          ],
          [
            1499977530.781,
            "0"
          ],
          [
            1499977830.781,
            "0"
          ],
          [
            1499978130.781,
            "0"
          ],
          [
            1499978430.781,
            "0"
          ],
          [
            1499978730.781,
            "0"
          ],
          [
            1499979030.781,
            "0"
          ],
          [
            1499979330.781,
            "0"
          ],
          [
            1499979630.781,
            "0"
          ],
          [
            1499979930.781,
            "0"
          ],
          [
            1499980230.781,
            "0"
          ],
          [
            1499980530.781,
            "0"
          ],
          [
            1499980830.781,
            "0"
          ],
          [
            1499981130.781,
            "0"
          ],
          [
            1499981430.781,
            "0"
          ],
          [
            1499981730.781,
            "0"
          ],
          [
            1499982030.781,
            "0"
          ],
          [
            1499982330.781,
            "0"
          ],
          [
            1499982630.781,
            "0"
          ],
          [
            1499982930.781,
            "0"
          ],
          [
            1499983230.781,
            "0"
          ],
          [
            1499983530.781,
            "0"
          ],
          [
            1499983830.781,
            "0"
          ],
          [
            1499984130.781,
            "0"
          ],
          [
            1499984430.781,
            "0"
          ],
          [
            1499984730.781,
            "0"
          ],
          [
            1499985030.781,
            "0"
          ],
          [
            1499985330.781,
            "0"
          ],
          [
            1499985630.781,
            "0"
          ],
          [
            1499985930.781,
            "0"
          ],
          [
            1499986230.781,
            "0"
          ],
          [
            1499986530.781,
            "0"
          ],
          [
            1499986830.781,
            "0"
          ],
          [
            1499987130.781,
            "0"
          ],
          [
            1499987430.781,
            "0"
          ],
          [
            1499987730.781,
            "0"
          ],
          [
            1499988030.781,
            "0"
          ],
          [
            1499988330.781,
            "0"
          ],
          [
            1499988630.781,
            "0"
          ],
          [
            1499988930.781,
            "0"
          ],
          [
            1499989230.781,
            "0"
          ],
          [
            1499989530.781,
            "0"
          ],
          [
            1499989830.781,
            "0"
          ],
          [
            1499990130.781,
            "0"
          ],
          [
            1499990430.781,
            "0"
          ],
          [
            1499990730.781,
            "0"
          ],
          [
            1499991030.781,
            "0"
          ],
          [
            1499991330.781,
            "0"
          ],
          [
            1499991630.781,
            "0"
          ],
          [
            1499991930.781,
            "0"
          ],
          [
            1499992230.781,
            "0"
          ],
          [
            1499992530.781,
            "0"
          ],
          [
            1499992830.781,
            "0"
          ],
          [
            1499993130.781,
            "0"
          ],
          [
            1499993430.781,
            "0"
          ],
          [
            1499993730.781,
            "0"
          ],
          [
            1499994030.781,
            "0"
          ],
          [
            1499994330.781,
            "0"
          ],
          [
            1499994630.781,
            "0"
          ],
          [
            1499994930.781,
            "0"
          ],
          [
            1499995230.781,
            "0"
          ],
          [
            1499995530.781,
            "0"
          ],
          [
            1499995830.781,
            "0"
          ],
          [
            1499996130.781,
            "0"
          ],
          [
            1499996430.781,
            "0"
          ],
          [
            1499996730.781,
            "0"
          ],
          [
            1499997030.781,
            "0"
          ],
          [
            1499997330.781,
            "0"
          ],
          [
            1499997630.781,
            "0"
          ],
          [
            1499997930.781,
            "0"
          ],
          [
            1499998230.781,
            "0"
          ],
          [
            1499998530.781,
            "0"
          ],
          [
            1499998830.781,
            "0"
          ],
          [
            1499999130.781,
            "0"
          ],
          [
            1499999430.781,
            "0"
          ],
          [
            1499999730.781,
            "0"
          ],
          [
            1500000030.781,
            "0"
          ],
          [
            1500000330.781,
            "0"
          ],
          [
            1500000630.781,
            "0"
          ],
          [
            1500000930.781,
            "0"
          ],
          [
            1500001230.781,
            "0"
          ],
          [
            1500001530.781,
            "0"
          ],
          [
            1500001830.781,
            "0"
          ],
          [
            1500002130.781,
            "0"
          ],
          [
            1500002430.781,
            "0"
          ],
          [
            1500002730.781,
            "0"
          ],
          [
            1500003030.781,
            "0"
          ],
          [
            1500003330.781,
            "0"
          ],
          [
            1500003630.781,
            "0"
          ],
          [
            1500003930.781,
            "0"
          ],
          [
            1500004230.781,
            "0"
          ],
          [
            1500004530.781,
            "0"
          ],
          [
            1500004830.781,
            "0"
          ],
          [
            1500005130.781,
            "0"
          ],
          [
            1500005430.781,
            "0"
          ],
          [
            1500005730.781,
            "0"
          ],
          [
            1500006030.781,
            "0"
          ],
          [
            1500006330.781,
            "0"
          ],
          [
            1500006630.781,
            "0"
          ],
          [
            1500006930.781,
            "0"
          ],
          [
            1500007230.781,
            "0"
          ],
          [
            1500007530.781,
            "0"
          ],
          [
            1500007830.781,
            "0"
          ],
          [
            1500008130.781,
            "0"
          ],
          [
            1500008430.781,
            "0"
          ],
          [
            1500008730.781,
            "0"
          ],
          [
            1500009030.781,
            "0"
          ],
          [
            1500009330.781,
            "0"
          ],
          [
            1500009630.781,
            "0"
          ],
          [
            1500009930.781,
            "0"
          ],
          [
            1500010230.781,
            "0"
          ],
          [
            1500010530.781,
            "0"
          ],
          [
            1500010830.781,
            "0"
          ],
          [
            1500011130.781,
            "0"
          ],
          [
            1500011430.781,
            "0"
          ],
          [
            1500011730.781,
            "0"
          ],
          [
            1500012030.781,
            "0"
          ],
          [
            1500012330.781,
            "0"
          ],
          [
            1500012630.781,
            "0"
          ],
          [
            1500012930.781,
            "0"
          ],
          [
            1500013230.781,
            "0"
          ],
          [
            1500013530.781,
            "0"
          ],
          [
            1500013830.781,
            "0"
          ],
          [
            1500014130.781,
            "0"
          ],
          [
            1500014430.781,
            "0"
          ],
          [
            1500014730.781,
            "0"
          ],
          [
            1500015030.781,
            "0"
          ],
          [
            1500015330.781,
            "0"
          ],
          [
            1500015630.781,
            "0"
          ],
          [
            1500015930.781,
            "0"
          ],
          [
            1500016230.781,
            "0"
          ],
          [
            1500016530.781,
            "0"
          ],
          [
            1500016830.781,
            "0"
          ],
          [
            1500017130.781,
            "0"
          ],
          [
            1500017430.781,
            "0"
          ],
          [
            1500017730.781,
            "0"
          ],
          [
            1500018030.781,
            "0"
          ],
          [
            1500018330.781,
            "0"
          ],
          [
            1500018630.781,
            "0"
          ],
          [
            1500018930.781,
            "0"
          ],
          [
            1500019230.781,
            "0"
          ],
          [
            1500019530.781,
            "0"
          ],
          [
            1500019830.781,
            "0"
          ],
          [
            1500020130.781,
            "0"
          ],
          [
            1500020430.781,
            "0"
          ],
          [
            1500020730.781,
            "0"
          ],
          [
            1500021030.781,
            "0"
          ],
          [
            1500021330.781,
            "0"
          ],
          [
            1500021630.781,
            "0"
          ],
          [
            1500021930.781,
            "0"
          ],
          [
            1500022230.781,
            "0"
          ],
          [
            1500022530.781,
            "0"
          ],
          [
            1500022830.781,
            "0"
          ],
          [
            1500023130.781,
            "0"
          ],
          [
            1500023430.781,
            "0"
          ],
          [
            1500023730.781,
            "0"
          ],
          [
            1500024030.781,
            "0"
          ],
          [
            1500024330.781,
            "0"
          ],
          [
            1500024630.781,
            "0"
          ],
          [
            1500024930.781,
            "0"
          ],
          [
            1500025230.781,
            "0"
          ],
          [
            1500025530.781,
            "0"
          ],
          [
            1500025830.781,
            "0"
          ],
          [
            1500026130.781,
            "0"
          ],
          [
            1500026430.781,
            "0"
          ],
          [
            1500026730.781,
            "0"
          ],
          [
            1500027030.781,
            "0"
          ],
          [
            1500027330.781,
            "0"
          ],
          [
            1500027630.781,
            "0"
          ],
          [
            1500027930.781,
            "0"
          ],
          [
            1500028230.781,
            "0"
          ],
          [
            1500028530.781,
            "0"
          ],
          [
            1500028830.781,
            "0"
          ],
          [
            1500029130.781,
            "0"
          ],
          [
            1500029430.781,
            "0"
          ],
          [
            1500029730.781,
            "0"
          ],
          [
            1500030030.781,
            "0"
          ],
          [
            1500030330.781,
            "0"
          ],
          [
            1500030630.781,
            "0"
          ],
          [
            1500030930.781,
            "0"
          ],
          [
            1500031230.781,
            "0"
          ],
          [
            1500031530.781,
            "0"
          ],
          [
            1500031830.781,
            "0"
          ],
          [
            1500032130.781,
            "0"
          ],
          [
            1500032430.781,
            "0"
          ],
          [
            1500032730.781,
            "0"
          ],
          [
            1500033030.781,
            "0"
          ],
          [
            1500033330.781,
            "0"
          ],
          [
            1500033630.781,
            "0"
          ],
          [
            1500033930.781,
            "0"
          ],
          [
            1500034230.781,
            "0"
          ],
          [
            1500034530.781,
            "0"
          ],
          [
            1500034830.781,
            "0"
          ],
          [
            1500035130.781,
            "0"
          ],
          [
            1500035430.781,
            "0"
          ],
          [
            1500035730.781,
            "0"
          ],
          [
            1500036030.781,
            "0"
          ],
          [
            1500036330.781,
            "0"
          ],
          [
            1500036630.781,
            "0"
          ],
          [
            1500036930.781,
            "0"
          ],
          [
            1500037230.781,
            "0"
          ],
          [
            1500037530.781,
            "0"
          ],
          [
            1500037830.781,
            "0"
          ],
          [
            1500038130.781,
            "0"
          ],
          [
            1500038430.781,
            "0"
          ],
          [
            1500038730.781,
            "0"
          ],
          [
            1500039030.781,
            "0"
          ],
          [
            1500039330.781,
            "0"
          ],
          [
            1500039630.781,
            "0"
          ],
          [
            1500039930.781,
            "0"
          ],
          [
            1500040230.781,
            "0"
          ],
          [
            1500040530.781,
            "0"
          ],
          [
            1500040830.781,
            "0"
          ],
          [
            1500041130.781,
            "0"
          ],
          [
            1500041430.781,
            "0"
          ],
          [
            1500041730.781,
            "0"
          ],
          [
            1500042030.781,
            "0"
          ],
          [
            1500042330.781,
            "0"
          ],
          [
            1500042630.781,
            "0"
          ],
          [
            1500042930.781,
            "0"
          ],
          [
            1500043230.781,
            "0"
          ],
          [
            1500043530.781,
            "0"
          ],
          [
            1500043830.781,
            "0"
          ],
          [
            1500044130.781,
            "0"
          ],
          [
            1500044430.781,
            "0"
          ],
          [
            1500044730.781,
            "0"
          ],
          [
            1500045030.781,
            "0"
          ],
          [
            1500045330.781,
            "0"
          ],
          [
            1500045630.781,
            "0"
          ],
          [
            1500045930.781,
            "0"
          ],
          [
            1500046230.781,
            "0"
          ],
          [
            1500046530.781,
            "0"
          ],
          [
            1500046830.781,
            "0"
          ],
          [
            1500047130.781,
            "0"
          ],
          [
            1500047430.781,
            "0"
          ],
          [
            1500047730.781,
            "0"
          ],
          [
            1500048030.781,
            "0"
          ],
          [
            1500048330.781,
            "0"
          ],
          [
            1500048630.781,
            "0"
          ],
          [
            1500048930.781,
            "0"
          ],
          [
            1500049230.781,
            "0"
          ],
          [
            1500049530.781,
            "0"
          ],
          [
            1500049830.781,
            "0"
          ],
          [
            1500050130.781,
            "0"
          ],
          [
            1500050430.781,
            "0"
          ],
          [
            1500050730.781,
            "0"
          ],
          [
            1500051030.781,
            "0"
          ],
          [
            1500051330.781,
            "0"
          ],
          [
            1500051630.781,
            "0"
          ],
          [
            1500051930.781,
            "0"
          ],
          [
            1500052230.781,
            "0"
          ],
          [
            1500052530.781,
            "0"
          ],
          [
            1500052830.781,
            "0"
          ],
          [
            1500053130.781,
            "0"
          ],
          [
            1500053430.781,
            "0"
          ],
          [
            1500053730.781,
            "0"
          ],
          [
            1500054030.781,
            "0"
          ],
          [
            1500054330.781,
            "0"
          ],
          [
            1500054630.781,
            "0"
          ],
          [
            1500054930.781,
            "0"
          ],
          [
            1500055230.781,
            "0"
          ],
          [
            1500055530.781,
            "0"
          ],
          [
            1500055830.781,
            "0"
          ],
          [
            1500056130.781,
            "0"
          ],
          [
            1500056430.781,
            "0"
          ],
          [
            1500056730.781,
            "0"
          ],
          [
            1500057030.781,
            "0"
          ],
          [
            1500057330.781,
            "0"
          ],
          [
            1500057630.781,
            "0"
          ],
          [
            1500057930.781,
            "0"
          ],
          [
            1500058230.781,
            "0"
          ],
          [
            1500058530.781,
            "0"
          ],
          [
            1500058830.781,
            "0"
          ],
          [
            1500059130.781,
            "0"
          ],
          [
            1500059430.781,
            "0"
          ],
          [
            1500059730.781,
            "0"
          ],
          [
            1500060030.781,
            "0"
          ],
          [
            1500060330.781,
            "0"
          ],
          [
            1500060630.781,
            "0"
          ],
          [
            1500060930.781,
            "0"
          ],
          [
            1500061230.781,
            "0"
          ],
          [
            1500061530.781,
            "0"
          ],
          [
            1500061830.781,
            "0"
          ],
          [
            1500062130.781,
            "0"
          ],
          [
            1500062430.781,
            "0"
          ],
          [
            1500062730.781,
            "0"
          ],
          [
            1500063030.781,
            "0"
          ]
        ]
      }
    ]
  }
}
